Metadata-Version: 1.1
Name: score-component
Version: 0.4.3
Summary: React music components for my own project
Home-page: UNKNOWN
Author: Uljas Pulkkis <uljas.pulkkis@gmail.com>
Author-email: UNKNOWN
License: MIT
Platform: UNKNOWN
Classifier: Framework :: Dash
